ovos_ww_plugin_precise_lite/__init__.py
ovos_ww_plugin_precise_lite/version.py
ovos_ww_plugin_precise_lite-0.1.6.dist-info/LICENSE
ovos_ww_plugin_precise_lite-0.1.6.dist-info/METADATA
ovos_ww_plugin_precise_lite-0.1.6.dist-info/WHEEL
ovos_ww_plugin_precise_lite-0.1.6.dist-info/entry_points.txt
ovos_ww_plugin_precise_lite-0.1.6.dist-info/top_level.txt
ovos_ww_plugin_precise_lite-0.1.6.dist-info/zip-safe
ovos_ww_plugin_precise_lite-0.1.6.dist-info/RECORD
