Metadata-Version: 2.1
Name: ovos-ww-plugin-precise-lite
Version: 0.1.6
Summary: A wake word plugin for OpenVoiceOS
Home-page: https://github.com/OpenVoiceOS/ovos-ww-plugin-precise-lite
Author: JarbasAi
Author-email: jarbasai@mailfence.com
License: Apache-2.0
Keywords: mycroft ovos plugin wake word
Classifier: Development Status :: 3 - Alpha
Classifier: Intended Audience :: Developers
Classifier: Topic :: Text Processing :: Linguistic
Classifier: License :: OSI Approved :: Apache Software License
Classifier: Programming Language :: Python :: 2
Classifier: Programming Language :: Python :: 2.7
Classifier: Programming Language :: Python :: 3
Classifier: Programming Language :: Python :: 3.0
Classifier: Programming Language :: Python :: 3.1
Classifier: Programming Language :: Python :: 3.2
Classifier: Programming Language :: Python :: 3.3
Classifier: Programming Language :: Python :: 3.4
Classifier: Programming Language :: Python :: 3.5
Classifier: Programming Language :: Python :: 3.6
License-File: LICENSE
Requires-Dist: precise-lite-runner<1.0.0,>=0.4.1
Requires-Dist: ovos-plugin-manager<2.0.0,>=1.0.0
Requires-Dist: ovos-utils<1.0.0,>=0.0.14
Provides-Extra: full
Requires-Dist: tensorflow; extra == "full"
Provides-Extra: tflite
Requires-Dist: tflite-runtime~=2.0; extra == "tflite"
Requires-Dist: numpy~=1.0; extra == "tflite"
